bsb_yaml/__init__.py
bsb_yaml/components.py
bsb_yaml/parser.py
bsb_yaml/templates/__init__.py
bsb_yaml/templates/skeleton.yaml
bsb_yaml/templates/starting_example.yaml
bsb_yaml-7.2.1.dist-info/entry_points.txt
bsb_yaml-7.2.1.dist-info/licenses/LICENSE
bsb_yaml-7.2.1.dist-info/WHEEL
bsb_yaml-7.2.1.dist-info/METADATA
bsb_yaml-7.2.1.dist-info/RECORD
