Metadata-Version: 2.4
Name: bsb-yaml
Version: 7.2.1
Summary: YAML parser for the BSB framework.
Author-email: Robin De Schepper <robin@alexandria.sc>, Dimitri Rodarie <dimitri.rodarie@unipv.it>
Requires-Python: >=3.10,<4
Classifier: License :: OSI Approved :: GNU General Public License v3 or later (GPLv3+)
License-File: LICENSE
Requires-Dist: bsb-core~=7.0
Requires-Dist: PyYAML~=6.0
Requires-Dist: pydantic
